dcitools/__init__.py
dcitools/devices/__init__.py
dcitools/devices/doremi/__init__.py
dcitools/devices/doremi/cli.py
dcitools/devices/doremi/commands.py
dcitools/devices/doremi/http.py
dcitools/devices/doremi/message.py
dcitools/devices/doremi/requests.py
dcitools/devices/doremi/responses.py
dcitools/devices/doremi/server.py
dcitools/devices/doremi/snmp.py
dcitools/parsers/__init__.py
dcitools/parsers/cpl.py
dcitools/parsers/spl.py
dcitools-0.7.2.data/scripts/doremiapi
dcitools-0.7.2.dist-info/LICENCE.txt
dcitools-0.7.2.dist-info/METADATA
dcitools-0.7.2.dist-info/WHEEL
dcitools-0.7.2.dist-info/top_level.txt
dcitools-0.7.2.dist-info/RECORD
