Metadata-Version: 2.1
Name: dcitools
Version: 0.7.2
Summary: Digital Cinema related collection of tools for Python
Home-page: https://github.com/ronhanson/python-dcitools
Author: Ronan Delacroix
Author-email: ronan.delacroix@gmail.com
License: The MIT License (MIT)
Requires-Dist: tbx (>=1.9.4)
Requires-Dist: six (>=1.8.0)
Requires-Dist: pysnmp (>=4.2.5)
Requires-Dist: bottle
